logall/__init__.py
logall/logclasses.py
logall/utils.py
logall-0.0.4.dist-info/LICENSE
logall-0.0.4.dist-info/METADATA
logall-0.0.4.dist-info/WHEEL
logall-0.0.4.dist-info/top_level.txt
logall-0.0.4.dist-info/RECORD
