Metadata-Version: 2.1
Name: logall
Version: 0.0.4
Summary: Unifies metric logging from various logging packages
Home-page: https://github.com/fvarno/logall
Author: Farshid Varno
Author-email: fr.varno@gmail.com
License: Apache-2.0
Project-URL: Documentation, https://logall.readthedocs.io/
Project-URL: Changelog, https://logall.readthedocs.io/en/latest/changelog.html
Project-URL: Issue Tracker, https://github.com/fvarno/logall/issues
Keywords: tensorboard,mlflow,logging,polyaxon
Platform: any
Classifier: Development Status :: 2 - Pre-Alpha
Classifier: Intended Audience :: Developers
Classifier: Intended Audience :: Education
Classifier: License :: OSI Approved :: Apache Software License
Classifier: Operating System :: Unix
Classifier: Operating System :: POSIX
Classifier: Operating System :: Microsoft :: Windows
Classifier: Intended Audience :: Science/Research
Classifier: Intended Audience :: Information Technology
Classifier: License :: OSI Approved :: Apache Software License
Classifier: Topic :: Scientific/Engineering
Classifier: Topic :: Scientific/Engineering :: Mathematics
Classifier: Topic :: Scientific/Engineering :: Artificial Intelligence
Classifier: Topic :: Software Development
Classifier: Topic :: Software Development :: Libraries
Classifier: Topic :: Software Development :: Libraries :: Python Modules
Classifier: Programming Language :: Python
Classifier: Programming Language :: Python :: 3
Classifier: Programming Language :: Python :: 3 :: Only
Classifier: Programming Language :: Python :: 3.9
Classifier: Programming Language :: Python :: 3.10
Classifier: Topic :: Utilities
Requires-Python: >=3.6
License-File: LICENSE
Requires-Dist: torch
Requires-Dist: tensorboard
Requires-Dist: polyaxon
Requires-Dist: mlflow
Provides-Extra: test
Requires-Dist: pytest ; extra == 'test'
Requires-Dist: pytest-cov ; extra == 'test'
Requires-Dist: codecov ; extra == 'test'
